gql_client/__init__.py
gql_client/compiler/__init__.py
gql_client/compiler/cli.py
gql_client/compiler/constant.py
gql_client/compiler/query_parser.py
gql_client/compiler/renderer_dataclasses.py
gql_client/compiler/utils_codegen.py
gql_client/compiler/utils_schema.py
gql_client/runtime/__init__.py
gql_client/runtime/enum_utils.py
gql_client/runtime/variables.py
py_gql_client-1.0.1.data/scripts/gql-compiler
py_gql_client-1.0.1.dist-info/LICENSE
py_gql_client-1.0.1.dist-info/METADATA
py_gql_client-1.0.1.dist-info/WHEEL
py_gql_client-1.0.1.dist-info/top_level.txt
py_gql_client-1.0.1.dist-info/RECORD
