Metadata-Version: 2.1
Name: py-gql-client
Version: 1.0.1
Summary: Python GraphQL generated code client
Home-page: UNKNOWN
Author: Facebook Inc.
License: BSD License
Platform: UNKNOWN
Classifier: License :: OSI Approved :: BSD License
Classifier: Programming Language :: Python :: 3.6
Classifier: Programming Language :: Python :: 3.7
Requires-Python: >=3.6
Requires-Dist: gql (>=v3.0.0a5)
Requires-Dist: dataclasses (==0.6)
Requires-Dist: dataclasses-json (==0.5.2)
